{
  "id": "API_0306",
  "result": [
    {
      "house_cnt": "3294",
      "adm_cd": "1124051",
      "adm_nm": "풍납1동"
    },
    {
      "house_cnt": "7472",
      "adm_cd": "1124052",
      "adm_nm": "풍납2동"
    },
    {
      "house_cnt": "3431",
      "adm_cd": "1124053",
      "adm_nm": "거여1동"
    },
    {
      "house_cnt": "5357",
      "adm_cd": "1124054",
      "adm_nm": "거여2동"
    },
    {
      "house_cnt": "5240",
      "adm_cd": "1124055",
      "adm_nm": "마천1동"
    },
    {
      "house_cnt": "5306",
      "adm_cd": "1124056",
      "adm_nm": "마천2동"
    },
    {
      "house_cnt": "4914",
      "adm_cd": "1124057",
      "adm_nm": "방이1동"
    },
    {
      "house_cnt": "7896",
      "adm_cd": "1124058",
      "adm_nm": "방이2동"
    },
    {
      "house_cnt": "5501",
      "adm_cd": "1124059",
      "adm_nm": "오륜동"
    },
    {
      "house_cnt": "12389",
      "adm_cd": "1124060",
      "adm_nm": "오금동"
    },
    {
      "house_cnt": "8989",
      "adm_cd": "1124061",
      "adm_nm": "송파1동"
    },
    {
      "house_cnt": "6460",
      "adm_cd": "1124062",
      "adm_nm": "송파2동"
    },
    {
      "house_cnt": "11860",
      "adm_cd": "1124063",
      "adm_nm": "석촌동"
    },
    {
      "house_cnt": "11182",
      "adm_cd": "1124064",
      "adm_nm": "삼전동"
    },
    {
      "house_cnt": "8249",
      "adm_cd": "1124065",
      "adm_nm": "가락본동"
    },
    {
      "house_cnt": "9556",
      "adm_cd": "1124066",
      "adm_nm": "가락1동"
    },
    {
      "house_cnt": "10205",
      "adm_cd": "1124067",
      "adm_nm": "가락2동"
    },
    {
      "house_cnt": "6755",
      "adm_cd": "1124068",
      "adm_nm": "문정1동"
    },
    {
      "house_cnt": "5543",
      "adm_cd": "1124069",
      "adm_nm": "문정2동"
    },
    {
      "house_cnt": "9370",
      "adm_cd": "1124071",
      "adm_nm": "잠실본동"
    },
    {
      "house_cnt": "6790",
      "adm_cd": "1124075",
      "adm_nm": "잠실4동"
    },
    {
      "house_cnt": "5228",
      "adm_cd": "1124077",
      "adm_nm": "잠실6동"
    },
    {
      "house_cnt": "3161",
      "adm_cd": "1124078",
      "adm_nm": "잠실7동"
    },
    {
      "house_cnt": "11039",
      "adm_cd": "1124079",
      "adm_nm": "잠실2동"
    },
    {
      "house_cnt": "10927",
      "adm_cd": "1124080",
      "adm_nm": "잠실3동"
    },
    {
      "house_cnt": "10522",
      "adm_cd": "1124081",
      "adm_nm": "장지동"
    },
    {
      "house_cnt": "8781",
      "adm_cd": "1124082",
      "adm_nm": "위례동"
    }
  ],
  "errMsg": "Success",
  "errCd": 0,
  "trId": "Jn=v_API_0306_1655685632323"
}
